SignExtend.sv
module SignExtend #(parameter INSTR_WIDTH = 32)(
    input logic [INSTR_WIDTH-1:0] Instr,
    input logic [1:0] ImmSrc,
    output logic [INSTR_WIDTH-1:0] ImmOp 
);

always_comb 
    case (ImmSrc)
        2'b00 : ImmOp={{20{Instr[31]}},Instr[31:20]};
        2'b01 : ImmOp={{20{Instr[31]}},Instr[31:25],Instr[11:7]};
        2'b10 : ImmOp={{20{Instr[31]}},Instr[7],Instr[30:25],Instr[11:8],1'b0};
    endcase

    
endmodule

ControlUnit.sv
module ControlUnit #(
    parameter DATA_WIDTH=32
)(
    input logic[DATA_WIDTH-1:0] Instr,
    input logic EQ,
    output logic [1:0] ImmSrc,
    output logic PCsrc,
    output logic [2:0] ALUctrl,
    output logic ALUsrc,
    output logic RegWrite
); 

logic [6:0] op= Instr[6:0];
logic [2:0] funct3 = Instr[14:12];
logic [6:0] funct7 = Instr[31:25];
logic Branch;


always_comb begin
    case (op)
        // 7'd3: begin
        //   ALUctrl=3'b000;
        //   ImmSrc=2'b00;
        //   RegWrite=1;
        //   ALUsrc=1;
        //   Branch=0;
        // end
   
        
        7'd19: begin
            case (funct3) 
                    3'b000: 
                            ALUctrl=3'b000;
                    3'b010: ALUctrl=3'b101;
                    3'b110: ALUctrl=3'b011;
                    3'b111: ALUctrl=3'b010;
            
            endcase
            Branch=0;
            ALUsrc=1;
            RegWrite=1;
            ImmSrc=2'b00;
            PCsrc=0;
        end
        // 7'd51:
        //        case (funct3) 
        //             3'b000: 
        //                 if ({op[5],funct7[5]}==2'b11)
        //                     ALUctrl=3'b001;
        //                 else
        //                     ALUctrl=3'b000;
        //             3'b010: ALUctrl=3'b101;
        //             3'b110: ALUctrl=3'b011;
        //             3'b111: ALUctrl=3'b010;
            
        //     endcase
        //     Branch=0;
        //     ALUsrc=0;
        //     RegWrite=1;
        // 7'd35:
        7'd99:   begin
            ALUctrl=3'b001;
            ImmSrc=2'b10;
            Branch=1;
            case (funct3)
             3'b000: PCsrc=(Branch&EQ);
             3'b001: PCsrc=(Branch&!EQ);
            endcase
            RegWrite=0;
        end
    endcase
    
end
endmodule

InstrMem.sv
module InstrMem #(
    parameter ADDRESS_WIDTH  = 8,
                DATA_WIDTH = 32
)(
    input logic [ADDRESS_WIDTH-1:0] addr,
    output logic [DATA_WIDTH-1:0] dout
);

logic [DATA_WIDTH-1:0] rom_array [2**ADDRESS_WIDTH-1:0];

initial begin 
    $display("Loading rom...");
    $readmemh("test.mem",rom_array);
end;

always_comb begin
    dout = rom_array [addr];
   
end 
endmodule

ControlPath.sv
module ControlPath #(parameter DATA_WIDTH=32, REG_ADDRESS_WIDTH=5, MEM_ADDRESS_WIDTH=8)(
    input logic [MEM_ADDRESS_WIDTH-1:0] PC,
    input logic EQ,
    output logic [DATA_WIDTH-1:0] ImmOp,
    output logic ALUsrc,
    output logic [2:0] ALUctrl,
    output logic RegWrite,
    output logic [REG_ADDRESS_WIDTH-1:0] rs1,
    output logic [REG_ADDRESS_WIDTH-1:0] rs2,
    output logic [REG_ADDRESS_WIDTH-1:0] rd,
    output logic PCsrc

);

logic [1:0] ImmSrc;
logic [DATA_WIDTH-1:0] Instr;


InstrMem instrMem(
    .addr(PC),
    .dout(Instr)
);
ControlUnit controlUnit(
    .Instr(Instr),
    .EQ(EQ),
    .RegWrite(RegWrite),
    .ImmSrc(ImmSrc),
    .PCsrc(PCsrc),
    .ALUctrl(ALUctrl),
    .ALUsrc(ALUsrc)
);
SignExtend signExtend(
    .ImmSrc(ImmSrc),
    .Instr(Instr),
    .ImmOp(ImmOp)
);

always_comb begin
    rs2=Instr[24:20];
    rs1=Instr[19:15];
    rd=Instr[11:7];
end
endmodule

PC.sv
module PC#(parameter MEM_ADDRESS_WIDTH=8)(
    input logic clk,
    input logic rst,
    input logic [MEM_ADDRESS_WIDTH-1:0] next_PC,
    output logic [MEM_ADDRESS_WIDTH-1:0] PC
);

always_ff @(posedge clk)begin 
    if(rst)
        PC={MEM_ADDRESS_WIDTH{1'b0}};
    else
        PC=next_PC;
end

endmodule

MUX.sv
module MUX#(parameter DATA_WIDTH=32)(
    input logic [DATA_WIDTH-1:0] a, 
    input logic [DATA_WIDTH-1:0]b,
    input logic sel,
    output logic [DATA_WIDTH-1:0] out
);

always_comb begin
    if(sel==0)
        out=a;
    else
        out=b;
end

endmodule

ALU.sv
module ALU #(parameter DATA_WIDTH=32)(
    input logic [DATA_WIDTH-1:0] op1, 
    input logic [DATA_WIDTH-1:0] op2,
    input logic [2:0] ctrl,
    output logic [DATA_WIDTH-1:0] sum,
    output logic eq
);

always_comb begin
    case (ctrl)
    3'b000: sum = op1 + op2;
    3'b001: sum = op1 - op2;
    3'b010: sum = op1 & op2;
    3'b011: sum = op1 | op2;
        
    endcase

    assign eq= (op1 == op2);
   
end

endmodule

RegFile.sv
     
module RegFile #(
    parameter ADDRESS_WIDTH=5,
              DATA_WIDTH=32
)(
    input logic clk, 
    input logic we3,
    input logic[ADDRESS_WIDTH-1:0] ad1,
    input logic[ADDRESS_WIDTH-1:0] ad2, 
    input logic[ADDRESS_WIDTH-1:0]ad3,
    input logic [DATA_WIDTH-1:0] wd3,
    output logic[DATA_WIDTH-1:0] rd1, 
    output logic[DATA_WIDTH-1:0] rd2,
    output logic [DATA_WIDTH-1:0]a0
);

logic [DATA_WIDTH-1:0] regArray [2**ADDRESS_WIDTH-1:0];

always_ff @(posedge clk) begin
    if(we3)begin
        regArray[ad3]<=wd3;
    end
end

always_comb begin 
    rd1=regArray[ad1];
    rd2=regArray[ad2];
    a0=regArray[10]; 
    
end

endmodule

DataPath.sv
module DataPath #(
    parameter MEM_ADDRESS_WIDTH=8,
    REG_ADDRESS_WIDTH=5,
    DATA_WIDTH=32)
(
    output logic EQ,
    output logic [MEM_ADDRESS_WIDTH-1:0] PC,
    output logic [DATA_WIDTH-1:0] a0,
    input logic [DATA_WIDTH-1:0] ImmOp,
    input logic [REG_ADDRESS_WIDTH-1:0] rs1,
    input logic [REG_ADDRESS_WIDTH-1:0] rs2,
    input logic [REG_ADDRESS_WIDTH-1:0] rd,
    input logic RegWrite,
    input logic ALUsrc,
    input logic [2:0] ALUctrl,
    input logic clk,
    input logic rst,
    input logic PCsrc
 );

logic [DATA_WIDTH-1:0] ALUout;
logic [DATA_WIDTH-1:0] ALUop1;
logic [DATA_WIDTH-1:0] ALUop2;
logic [DATA_WIDTH-1:0] regOp2;
logic [MEM_ADDRESS_WIDTH-1:0] next_PC;

RegFile #(REG_ADDRESS_WIDTH,DATA_WIDTH) regFile(
    .clk(clk),
    .ad1(rs1),
    .ad2(rs2),
    .ad3(rd),
    .we3(RegWrite),
    .wd3(ALUout),
    .rd1(ALUop1),
    .rd2(regOp2),
    .a0(a0)
);

MUX #(DATA_WIDTH) aluMux(
    .a(regOp2),
    .b(ImmOp),
    .sel(ALUsrc),
    .out(ALUop2)
);

ALU #(DATA_WIDTH) alu(
    .op1(ALUop1),
    .op2(ALUop2),
    .ctrl(ALUctrl),
    .sum(ALUout),
    .eq(EQ)
);


MUX #(MEM_ADDRESS_WIDTH) pcMux(
    .sel(PCsrc),
    .a(PC+8'd4),
    .b(PC+ImmOp[MEM_ADDRESS_WIDTH-1:0]),
    .out(next_PC)

);

PC #(MEM_ADDRESS_WIDTH) pcReg(
    .clk(clk),
    .rst(rst),
    .next_PC(next_PC),
    .PC(PC)
);
initial begin
    PC=0;
end
endmodule

CPU.sv
module CPU #(
    parameter DATA_WIDTH=32,
    parameter MEM_ADDRESS_WIDTH=8,
    parameter REG_ADDRESS_WIDTH=5
)(
    input logic clk,
    input logic rst,
    output logic [DATA_WIDTH-1:0] a0
);
logic [MEM_ADDRESS_WIDTH-1:0] PC;
logic EQ;
logic [DATA_WIDTH-1:0] ImmOp;
logic ALUsrc;
logic [2:0] ALUctrl;
logic RegWrite;
logic [REG_ADDRESS_WIDTH-1:0] rs1;
logic [REG_ADDRESS_WIDTH-1:0] rs2;
logic [REG_ADDRESS_WIDTH-1:0] rd;
logic PCsrc;

DataPath dataPath(
    .clk(clk),
    .rst(rst),
    .ImmOp(ImmOp),
    .rs1(rs1),
    .rs2(rs2),
    .rd(rd),
    .RegWrite(RegWrite),
    .ALUsrc(ALUsrc),
    .ALUctrl(ALUctrl),
    .PC(PC),
    .PCsrc(PCsrc),
    .a0(a0),
    .EQ(EQ)
);

ControlPath controlPath(
    .ImmOp(ImmOp),
    .rs1(rs1),
    .rs2(rs2),
    .rd(rd),
    .RegWrite(RegWrite),
    .ALUsrc(ALUsrc),
    .ALUctrl(ALUctrl),
    .PC(PC),
    .PCsrc(PCsrc),
    .EQ(EQ)
);



endmodule

CPU.vcd
$version Generated by VerilatedVcd $end
$date Sat Dec  3 00:08:14 2022 $end
$timescale 1ps $end

 $scope module TOP $end
  $var wire 32 \ a0 [31:0] $end
  $var wire  1 Z clk $end
  $var wire  1 [ rst $end
  $scope module CPU $end
   $var wire  3 ' ALUctrl [2:0] $end
   $var wire  1 & ALUsrc $end
   $var wire 32 ] DATA_WIDTH [31:0] $end
   $var wire  1 $ EQ $end
   $var wire 32 % ImmOp [31:0] $end
   $var wire 32 ^ MEM_ADDRESS_WIDTH [31:0] $end
   $var wire  8 # PC [7:0] $end
   $var wire  1 , PCsrc $end
   $var wire 32 _ REG_ADDRESS_WIDTH [31:0] $end
   $var wire  1 ( RegWrite $end
   $var wire 32 \ a0 [31:0] $end
   $var wire  1 Z clk $end
   $var wire  5 + rd [4:0] $end
   $var wire  5 ) rs1 [4:0] $end
   $var wire  5 * rs2 [4:0] $end
   $var wire  1 [ rst $end
   $scope module controlPath $end
    $var wire  3 ' ALUctrl [2:0] $end
    $var wire  1 & ALUsrc $end
    $var wire 32 ] DATA_WIDTH [31:0] $end
    $var wire  1 $ EQ $end
    $var wire 32 % ImmOp [31:0] $end
    $var wire  2 - ImmSrc [1:0] $end
    $var wire 32 . Instr [31:0] $end
    $var wire 32 ^ MEM_ADDRESS_WIDTH [31:0] $end
    $var wire  8 # PC [7:0] $end
    $var wire  1 , PCsrc $end
    $var wire 32 _ REG_ADDRESS_WIDTH [31:0] $end
    $var wire  1 ( RegWrite $end
    $var wire  5 + rd [4:0] $end
    $var wire  5 ) rs1 [4:0] $end
    $var wire  5 * rs2 [4:0] $end
    $scope module controlUnit $end
     $var wire  3 ' ALUctrl [2:0] $end
     $var wire  1 & ALUsrc $end
     $var wire  1 2 Branch $end
     $var wire 32 ] DATA_WIDTH [31:0] $end
     $var wire  1 $ EQ $end
     $var wire  2 - ImmSrc [1:0] $end
     $var wire 32 . Instr [31:0] $end
     $var wire  1 , PCsrc $end
     $var wire  1 ( RegWrite $end
     $var wire  3 0 funct3 [2:0] $end
     $var wire  7 1 funct7 [6:0] $end
     $var wire  7 / op [6:0] $end
    $upscope $end
    $scope module instrMem $end
     $var wire 32 ^ ADDRESS_WIDTH [31:0] $end
     $var wire 32 ] DATA_WIDTH [31:0] $end
     $var wire  8 # addr [7:0] $end
     $var wire 32 . dout [31:0] $end
    $upscope $end
    $scope module signExtend $end
     $var wire 32 ] INSTR_WIDTH [31:0] $end
     $var wire 32 % ImmOp [31:0] $end
     $var wire  2 - ImmSrc [1:0] $end
     $var wire 32 . Instr [31:0] $end
    $upscope $end
   $upscope $end
   $scope module dataPath $end
    $var wire  3 ' ALUctrl [2:0] $end
    $var wire 32 4 ALUop1 [31:0] $end
    $var wire 32 5 ALUop2 [31:0] $end
    $var wire 32 3 ALUout [31:0] $end
    $var wire  1 & ALUsrc $end
    $var wire 32 ] DATA_WIDTH [31:0] $end
    $var wire  1 $ EQ $end
    $var wire 32 % ImmOp [31:0] $end
    $var wire 32 ^ MEM_ADDRESS_WIDTH [31:0] $end
    $var wire  8 # PC [7:0] $end
    $var wire  1 , PCsrc $end
    $var wire 32 _ REG_ADDRESS_WIDTH [31:0] $end
    $var wire  1 ( RegWrite $end
    $var wire 32 \ a0 [31:0] $end
    $var wire  1 Z clk $end
    $var wire  8 7 next_PC [7:0] $end
    $var wire  5 + rd [4:0] $end
    $var wire 32 6 regOp2 [31:0] $end
    $var wire  5 ) rs1 [4:0] $end
    $var wire  5 * rs2 [4:0] $end
    $var wire  1 [ rst $end
    $scope module alu $end
     $var wire 32 ] DATA_WIDTH [31:0] $end
     $var wire  3 ' ctrl [2:0] $end
     $var wire  1 $ eq $end
     $var wire 32 4 op1 [31:0] $end
     $var wire 32 5 op2 [31:0] $end
     $var wire 32 3 sum [31:0] $end
    $upscope $end
    $scope module aluMux $end
     $var wire 32 ] DATA_WIDTH [31:0] $end
     $var wire 32 6 a [31:0] $end
     $var wire 32 % b [31:0] $end
     $var wire 32 5 out [31:0] $end
     $var wire  1 & sel $end
    $upscope $end
    $scope module pcMux $end
     $var wire 32 ^ DATA_WIDTH [31:0] $end
     $var wire  8 8 a [7:0] $end
     $var wire  8 9 b [7:0] $end
     $var wire  8 7 out [7:0] $end
     $var wire  1 , sel $end
    $upscope $end
    $scope module pcReg $end
     $var wire 32 ^ MEM_ADDRESS_WIDTH [31:0] $end
     $var wire  8 # PC [7:0] $end
     $var wire  1 Z clk $end
     $var wire  8 7 next_PC [7:0] $end
     $var wire  1 [ rst $end
    $upscope $end
    $scope module regFile $end
     $var wire 32 _ ADDRESS_WIDTH [31:0] $end
     $var wire 32 ] DATA_WIDTH [31:0] $end
     $var wire 32 \ a0 [31:0] $end
     $var wire  5 ) ad1 [4:0] $end
     $var wire  5 * ad2 [4:0] $end
     $var wire  5 + ad3 [4:0] $end
     $var wire  1 Z clk $end
     $var wire 32 4 rd1 [31:0] $end
     $var wire 32 6 rd2 [31:0] $end
     $var wire 32 : regArray[0] [31:0] $end
     $var wire 32 D regArray[10] [31:0] $end
     $var wire 32 E regArray[11] [31:0] $end
     $var wire 32 F regArray[12] [31:0] $end
     $var wire 32 G regArray[13] [31:0] $end
     $var wire 32 H regArray[14] [31:0] $end
     $var wire 32 I regArray[15] [31:0] $end
     $var wire 32 J regArray[16] [31:0] $end
     $var wire 32 K regArray[17] [31:0] $end
     $var wire 32 L regArray[18] [31:0] $end
     $var wire 32 M regArray[19] [31:0] $end
     $var wire 32 ; regArray[1] [31:0] $end
     $var wire 32 N regArray[20] [31:0] $end
     $var wire 32 O regArray[21] [31:0] $end
     $var wire 32 P regArray[22] [31:0] $end
     $var wire 32 Q regArray[23] [31:0] $end
     $var wire 32 R regArray[24] [31:0] $end
     $var wire 32 S regArray[25] [31:0] $end
     $var wire 32 T regArray[26] [31:0] $end
     $var wire 32 U regArray[27] [31:0] $end
     $var wire 32 V regArray[28] [31:0] $end
     $var wire 32 W regArray[29] [31:0] $end
     $var wire 32 < regArray[2] [31:0] $end
     $var wire 32 X regArray[30] [31:0] $end
     $var wire 32 Y regArray[31] [31:0] $end
     $var wire 32 = regArray[3] [31:0] $end
     $var wire 32 > regArray[4] [31:0] $end
     $var wire 32 ? regArray[5] [31:0] $end
     $var wire 32 @ regArray[6] [31:0] $end
     $var wire 32 A regArray[7] [31:0] $end
     $var wire 32 B regArray[8] [31:0] $end
     $var wire 32 C regArray[9] [31:0] $end
     $var wire 32 3 wd3 [31:0] $end
     $var wire  1 ( we3 $end
    $upscope $end
   $upscope $end
  $upscope $end
 $upscope $end
$enddefinitions $end


#0
b00000000 #
0$
b00000000000000000000000000000000 %
0&
b000 '
0(
b00000 )
b00000 *
b00000 +
0,
b00 -
b00000000000000000000000000000000 .
b0000000 /
b000 0
b0000000 1
02
b00000000000000000000000000000000 3
b00000000000000000000000000000000 4
b00000000000000000000000000000000 5
b00000000000000000000000000000000 6
b00000100 7
b00000100 8
b00000000 9
b00000000000000000000000000000000 :
b00000000000000000000000000000000 ;
b00000000000000000000000000000000 <
b00000000000000000000000000000000 =
b00000000000000000000000000000000 >
b00000000000000000000000000000000 ?
b00000000000000000000000000000000 @
b00000000000000000000000000000000 A
b00000000000000000000000000000000 B
b00000000000000000000000000000000 C
b00000000000000000000000000000000 D
b00000000000000000000000000000000 E
b00000000000000000000000000000000 F
b00000000000000000000000000000000 G
b00000000000000000000000000000000 H
b00000000000000000000000000000000 I
b00000000000000000000000000000000 J
b00000000000000000000000000000000 K
b00000000000000000000000000000000 L
b00000000000000000000000000000000 M
b00000000000000000000000000000000 N
b00000000000000000000000000000000 O
b00000000000000000000000000000000 P
b00000000000000000000000000000000 Q
b00000000000000000000000000000000 R
b00000000000000000000000000000000 S
b00000000000000000000000000000000 T
b00000000000000000000000000000000 U
b00000000000000000000000000000000 V
b00000000000000000000000000000000 W
b00000000000000000000000000000000 X
b00000000000000000000000000000000 Y
1Z
0[
b00000000000000000000000000000000 \
b00000000000000000000000000100000 ]
b00000000000000000000000000001000 ^
b00000000000000000000000000000101 _
#1
b00000000000000000000000011111111 %
1&
1(
b11111 *
b00110 +
b00001111111100000000001100010011 .
b0010011 /
b0000111 1
b00000000000000000000000011111111 3
b00000000000000000000000011111111 5
b11111111 9
0Z
#2
b00000100 #
1$
b00000000000000000000000000000000 %
b00000 *
b01010 +
b00000000000000000000010100010011 .
b0000000 1
b00000000000000000000000000000000 3
b00000000000000000000000000000000 5
b00001000 7
b00001000 8
b00000100 9
b00000000000000000000000011111111 @
1Z
#3
0Z
#4
b00001000 #
b01011 +
b00000000000000000000010110010011 .
b00001100 7
b00001100 8
b00001000 9
1Z
#5
0Z
#6
b00001100 #
b01011 )
b01010 +
b00000000000001011000010100010011 .
b00010000 7
b00010000 8
b00001100 9
1Z
#7
0Z
#8
b00010000 #
0$
b00000000000000000000000000000001 %
b00001 *
b01011 +
b00000000000101011000010110010011 .
b00000000000000000000000000000001 3
b00000000000000000000000000000001 5
b00010100 7
b00010100 8
b00010001 9
1Z
#9
0Z
#10
b00010100 #
b11111111111111111111111111111000 %
b001 '
0(
b00110 *
b11001 +
1,
b10 -
b11111110011001011001110011100011 .
b1100011 /
b001 0
b1111111 1
12
b00000000000000000000000000001001 3
b00000000000000000000000000000001 4
b11111111111111111111111111111000 5
b00000000000000000000000011111111 6
b00001100 7
b00011000 8
b00001100 9
b00000000000000000000000000000001 E
1Z
#11
0Z
#12
b00001100 #
b00000000000000000000000000000000 %
b000 '
1(
b00000 *
b01010 +
0,
b00 -
b00000000000001011000010100010011 .
b0010011 /
b000 0
b0000000 1
02
b00000000000000000000000000000001 3
b00000000000000000000000000000000 5
b00000000000000000000000000000000 6
b00010000 7
b00010000 8
1Z
#13
0Z
#14
b00010000 #
1$
b00000000000000000000000000000001 %
b00001 *
b01011 +
b00000000000101011000010110010011 .
b00000000000000000000000000000010 3
b00000000000000000000000000000001 5
b00010100 7
b00010100 8
b00010001 9
b00000000000000000000000000000001 D
1Z
b00000000000000000000000000000001 \
#15
0Z
#16
b00010100 #
0$
b11111111111111111111111111111000 %
b001 '
0(
b00110 *
b11001 +
1,
b10 -
b11111110011001011001110011100011 .
b1100011 /
b001 0
b1111111 1
12
b00000000000000000000000000001010 3
b00000000000000000000000000000010 4
b11111111111111111111111111111000 5
b00000000000000000000000011111111 6
b00001100 7
b00011000 8
b00001100 9
b00000000000000000000000000000010 E
1Z
#17
0Z
#18
b00001100 #
b00000000000000000000000000000000 %
b000 '
1(
b00000 *
b01010 +
0,
b00 -
b00000000000001011000010100010011 .
b0010011 /
b000 0
b0000000 1
02
b00000000000000000000000000000010 3
b00000000000000000000000000000000 5
b00000000000000000000000000000000 6
b00010000 7
b00010000 8
1Z
#19
0Z
#20
b00010000 #
b00000000000000000000000000000001 %
b00001 *
b01011 +
b00000000000101011000010110010011 .
b00000000000000000000000000000011 3
b00000000000000000000000000000001 5
b00010100 7
b00010100 8
b00010001 9
b00000000000000000000000000000010 D
1Z
b00000000000000000000000000000010 \
#21
0Z
#22
b00010100 #
b11111111111111111111111111111000 %
b001 '
0(
b00110 *
b11001 +
1,
b10 -
b11111110011001011001110011100011 .
b1100011 /
b001 0
b1111111 1
12
b00000000000000000000000000001011 3
b00000000000000000000000000000011 4
b11111111111111111111111111111000 5
b00000000000000000000000011111111 6
b00001100 7
b00011000 8
b00001100 9
b00000000000000000000000000000011 E
1Z
#23
0Z
#24
b00001100 #
b00000000000000000000000000000000 %
b000 '
1(
b00000 *
b01010 +
0,
b00 -
b00000000000001011000010100010011 .
b0010011 /
b000 0
b0000000 1
02
b00000000000000000000000000000011 3
b00000000000000000000000000000000 5
b00000000000000000000000000000000 6
b00010000 7
b00010000 8
1Z
#25
0Z
#26
b00010000 #
b00000000000000000000000000000001 %
b00001 *
b01011 +
b00000000000101011000010110010011 .
b00000000000000000000000000000100 3
b00000000000000000000000000000001 5
b00010100 7
b00010100 8
b00010001 9
b00000000000000000000000000000011 D
1Z
b00000000000000000000000000000011 \
#27
0Z
#28
b00010100 #
b11111111111111111111111111111000 %
b001 '
0(
b00110 *
b11001 +
1,
b10 -
b11111110011001011001110011100011 .
b1100011 /
b001 0
b1111111 1
12
b00000000000000000000000000001100 3
b00000000000000000000000000000100 4
b11111111111111111111111111111000 5
b00000000000000000000000011111111 6
b00001100 7
b00011000 8
b00001100 9
b00000000000000000000000000000100 E
1Z
#29
0Z
#30
b00001100 #
b00000000000000000000000000000000 %
b000 '
1(
b00000 *
b01010 +
0,
b00 -
b00000000000001011000010100010011 .
b0010011 /
b000 0
b0000000 1
02
b00000000000000000000000000000100 3
b00000000000000000000000000000000 5
b00000000000000000000000000000000 6
b00010000 7
b00010000 8
1Z
#31
0Z
#32
b00010000 #
b00000000000000000000000000000001 %
b00001 *
b01011 +
b00000000000101011000010110010011 .
b00000000000000000000000000000101 3
b00000000000000000000000000000001 5
b00010100 7
b00010100 8
b00010001 9
b00000000000000000000000000000100 D
1Z
b00000000000000000000000000000100 \
#33
0Z
#34
b00010100 #
b11111111111111111111111111111000 %
b001 '
0(
b00110 *
b11001 +
1,
b10 -
b11111110011001011001110011100011 .
b1100011 /
b001 0
b1111111 1
12
b00000000000000000000000000001101 3
b00000000000000000000000000000101 4
b11111111111111111111111111111000 5
b00000000000000000000000011111111 6
b00001100 7
b00011000 8
b00001100 9
b00000000000000000000000000000101 E
1Z
#35
0Z
#36
b00001100 #
b00000000000000000000000000000000 %
b000 '
1(
b00000 *
b01010 +
0,
b00 -
b00000000000001011000010100010011 .
b0010011 /
b000 0
b0000000 1
02
b00000000000000000000000000000101 3
b00000000000000000000000000000000 5
b00000000000000000000000000000000 6
b00010000 7
b00010000 8
1Z
#37
0Z
#38
b00010000 #
b00000000000000000000000000000001 %
b00001 *
b01011 +
b00000000000101011000010110010011 .
b00000000000000000000000000000110 3
b00000000000000000000000000000001 5
b00010100 7
b00010100 8
b00010001 9
b00000000000000000000000000000101 D
1Z
b00000000000000000000000000000101 \
#39
0Z
#40
b00010100 #
b11111111111111111111111111111000 %
b001 '
0(
b00110 *
b11001 +
1,
b10 -
b11111110011001011001110011100011 .
b1100011 /
b001 0
b1111111 1
12
b00000000000000000000000000001110 3
b00000000000000000000000000000110 4
b11111111111111111111111111111000 5
b00000000000000000000000011111111 6
b00001100 7
b00011000 8
b00001100 9
b00000000000000000000000000000110 E
1Z
#41
0Z
#42
b00001100 #
b00000000000000000000000000000000 %
b000 '
1(
b00000 *
b01010 +
0,
b00 -
b00000000000001011000010100010011 .
b0010011 /
b000 0
b0000000 1
02
b00000000000000000000000000000110 3
b00000000000000000000000000000000 5
b00000000000000000000000000000000 6
b00010000 7
b00010000 8
1Z
#43
0Z
#44
b00010000 #
b00000000000000000000000000000001 %
b00001 *
b01011 +
b00000000000101011000010110010011 .
b00000000000000000000000000000111 3
b00000000000000000000000000000001 5
b00010100 7
b00010100 8
b00010001 9
b00000000000000000000000000000110 D
1Z
b00000000000000000000000000000110 \
#45
0Z
#46
b00010100 #
b11111111111111111111111111111000 %
b001 '
0(
b00110 *
b11001 +
1,
b10 -
b11111110011001011001110011100011 .
b1100011 /
b001 0
b1111111 1
12
b00000000000000000000000000001111 3
b00000000000000000000000000000111 4
b11111111111111111111111111111000 5
b00000000000000000000000011111111 6
b00001100 7
b00011000 8
b00001100 9
b00000000000000000000000000000111 E
1Z
#47
0Z
#48
b00001100 #
b00000000000000000000000000000000 %
b000 '
1(
b00000 *
b01010 +
0,
b00 -
b00000000000001011000010100010011 .
b0010011 /
b000 0
b0000000 1
02
b00000000000000000000000000000111 3
b00000000000000000000000000000000 5
b00000000000000000000000000000000 6
b00010000 7
b00010000 8
1Z
#49
0Z
#50
b00010000 #
b00000000000000000000000000000001 %
b00001 *
b01011 +
b00000000000101011000010110010011 .
b00000000000000000000000000001000 3
b00000000000000000000000000000001 5
b00010100 7
b00010100 8
b00010001 9
b00000000000000000000000000000111 D
1Z
b00000000000000000000000000000111 \
#51
0Z
#52
b00010100 #
b11111111111111111111111111111000 %
b001 '
0(
b00110 *
b11001 +
1,
b10 -
b11111110011001011001110011100011 .
b1100011 /
b001 0
b1111111 1
12
b00000000000000000000000000010000 3
b00000000000000000000000000001000 4
b11111111111111111111111111111000 5
b00000000000000000000000011111111 6
b00001100 7
b00011000 8
b00001100 9
b00000000000000000000000000001000 E
1Z
#53
0Z
#54
b00001100 #
b00000000000000000000000000000000 %
b000 '
1(
b00000 *
b01010 +
0,
b00 -
b00000000000001011000010100010011 .
b0010011 /
b000 0
b0000000 1
02
b00000000000000000000000000001000 3
b00000000000000000000000000000000 5
b00000000000000000000000000000000 6
b00010000 7
b00010000 8
1Z
#55
0Z
#56
b00010000 #
b00000000000000000000000000000001 %
b00001 *
b01011 +
b00000000000101011000010110010011 .
b00000000000000000000000000001001 3
b00000000000000000000000000000001 5
b00010100 7
b00010100 8
b00010001 9
b00000000000000000000000000001000 D
1Z
b00000000000000000000000000001000 \
#57
0Z
#58
b00010100 #
b11111111111111111111111111111000 %
b001 '
0(
b00110 *
b11001 +
1,
b10 -
b11111110011001011001110011100011 .
b1100011 /
b001 0
b1111111 1
12
b00000000000000000000000000010001 3
b00000000000000000000000000001001 4
b11111111111111111111111111111000 5
b00000000000000000000000011111111 6
b00001100 7
b00011000 8
b00001100 9
b00000000000000000000000000001001 E
1Z
#59
0Z
#60
b00001100 #
b00000000000000000000000000000000 %
b000 '
1(
b00000 *
b01010 +
0,
b00 -
b00000000000001011000010100010011 .
b0010011 /
b000 0
b0000000 1
02
b00000000000000000000000000001001 3
b00000000000000000000000000000000 5
b00000000000000000000000000000000 6
b00010000 7
b00010000 8
1Z
#61
0Z
#62
b00010000 #
b00000000000000000000000000000001 %
b00001 *
b01011 +
b00000000000101011000010110010011 .
b00000000000000000000000000001010 3
b00000000000000000000000000000001 5
b00010100 7
b00010100 8
b00010001 9
b00000000000000000000000000001001 D
1Z
b00000000000000000000000000001001 \
#63
0Z
#64
b00010100 #
b11111111111111111111111111111000 %
b001 '
0(
b00110 *
b11001 +
1,
b10 -
b11111110011001011001110011100011 .
b1100011 /
b001 0
b1111111 1
12
b00000000000000000000000000010010 3
b00000000000000000000000000001010 4
b11111111111111111111111111111000 5
b00000000000000000000000011111111 6
b00001100 7
b00011000 8
b00001100 9
b00000000000000000000000000001010 E
1Z
#65
0Z
#66
b00001100 #
b00000000000000000000000000000000 %
b000 '
1(
b00000 *
b01010 +
0,
b00 -
b00000000000001011000010100010011 .
b0010011 /
b000 0
b0000000 1
02
b00000000000000000000000000001010 3
b00000000000000000000000000000000 5
b00000000000000000000000000000000 6
b00010000 7
b00010000 8
1Z
#67
0Z
#68
b00010000 #
b00000000000000000000000000000001 %
b00001 *
b01011 +
b00000000000101011000010110010011 .
b00000000000000000000000000001011 3
b00000000000000000000000000000001 5
b00010100 7
b00010100 8
b00010001 9
b00000000000000000000000000001010 D
1Z
b00000000000000000000000000001010 \
#69
0Z
#70
b00010100 #
b11111111111111111111111111111000 %
b001 '
0(
b00110 *
b11001 +
1,
b10 -
b11111110011001011001110011100011 .
b1100011 /
b001 0
b1111111 1
12
b00000000000000000000000000010011 3
b00000000000000000000000000001011 4
b11111111111111111111111111111000 5
b00000000000000000000000011111111 6
b00001100 7
b00011000 8
b00001100 9
b00000000000000000000000000001011 E
1Z
#71
0Z
#72
b00001100 #
b00000000000000000000000000000000 %
b000 '
1(
b00000 *
b01010 +
0,
b00 -
b00000000000001011000010100010011 .
b0010011 /
b000 0
b0000000 1
02
b00000000000000000000000000001011 3
b00000000000000000000000000000000 5
b00000000000000000000000000000000 6
b00010000 7
b00010000 8
1Z
#73
0Z
#74
b00010000 #
b00000000000000000000000000000001 %
b00001 *
b01011 +
b00000000000101011000010110010011 .
b00000000000000000000000000001100 3
b00000000000000000000000000000001 5
b00010100 7
b00010100 8
b00010001 9
b00000000000000000000000000001011 D
1Z
b00000000000000000000000000001011 \
#75
0Z
#76
b00010100 #
b11111111111111111111111111111000 %
b001 '
0(
b00110 *
b11001 +
1,
b10 -
b11111110011001011001110011100011 .
b1100011 /
b001 0
b1111111 1
12
b00000000000000000000000000010100 3
b00000000000000000000000000001100 4
b11111111111111111111111111111000 5
b00000000000000000000000011111111 6
b00001100 7
b00011000 8
b00001100 9
b00000000000000000000000000001100 E
1Z
#77
0Z
#78
b00001100 #
b00000000000000000000000000000000 %
b000 '
1(
b00000 *
b01010 +
0,
b00 -
b00000000000001011000010100010011 .
b0010011 /
b000 0
b0000000 1
02
b00000000000000000000000000001100 3
b00000000000000000000000000000000 5
b00000000000000000000000000000000 6
b00010000 7
b00010000 8
1Z
#79
0Z
#80
b00010000 #
b00000000000000000000000000000001 %
b00001 *
b01011 +
b00000000000101011000010110010011 .
b00000000000000000000000000001101 3
b00000000000000000000000000000001 5
b00010100 7
b00010100 8
b00010001 9
b00000000000000000000000000001100 D
1Z
b00000000000000000000000000001100 \
#81
0Z
